<?xml version="1.0" encoding="UTF-8"?><apiPackage id="rx.internal"><apiName>rx.internal</apiName><apiDetail/><apiClassifier id="rx.internal:ErrorUtil"><apiName>ErrorUtil</apiName><shortdesc/><prolog><asMetadata/></prolog><apiClassifierDetail><apiClassifierDef><apiAccess value="public"/><apiStatic/><apiBaseClassifier>Object</apiBaseClassifier></apiClassifierDef></apiClassifierDetail><apiConstructor id="rx.internal:ErrorUtil:ErrorUtil"><apiName>ErrorUtil</apiName><shortdesc/><prolog/><apiConstructorDetail><apiConstructorDef><apiAccess value="public"/></apiConstructorDef></apiConstructorDetail></apiConstructor><apiOperation id="rx.internal:ErrorUtil:mapErrorEvent"><apiName>mapErrorEvent</apiName><shortdesc/><prolog/><apiOperationDetail><apiOperationDef><apiAccess value="public"/><apiStatic/><apiReturn><apiType value="Error"/></apiReturn><apiParam><apiItemName>errorEvent</apiItemName><apiType value="flash.events:ErrorEvent"/></apiParam></apiOperationDef></apiOperationDetail></apiOperation></apiClassifier></apiPackage>